[{"n": "Aggron #1", "p": 14.99, "p2": 470.51, "p3": 133.05, "d": -0.01, "dp": -0.1, "u": "aggron-1", "kart": true}, {"n": "Aggron [Reverse Holo] #1", "p": 17.3, "p2": 998.98, "p3": 60.75, "d": 0.0, "dp": 0.0, "u": "aggron-reverse-holo-1", "kart": true}, {"n": "Beautifly #2", "p": 13.45, "p2": 271.73, "p3": 62.47, "d": 0.0, "dp": 0.0, "u": "beautifly-2", "kart": true}, {"n": "Beautifly [Reverse Holo] #2", "p": 10.37, "p2": 133.61, "p3": 60.34, "d": 0.0, "dp": 0.0, "u": "beautifly-reverse-holo-2", "kart": true}, {"n": "Blaziken #3", "p": 7.59, "p2": 480.0, "p3": 400.0, "d": -0.41, "dp": -5.1, "u": "blaziken-3", "kart": true}, {"n": "Blaziken [Holo] #3", "p": 37.5, "p2": 3675.0, "p3": 328.65, "d": -3.23, "dp": -7.9, "u": "blaziken-holo-3", "kart": true}, {"n": "Blaziken [Reverse Holo] #3", "p": 39.38, "p2": 1463.5, "p3": 174.81, "d": 5.63, "dp": 16.7, "u": "blaziken-reverse-holo-3", "kart": true}, {"n": "Camerupt #4", "p": 13.0, "p2": 567.26, "p3": 94.27, "d": 0.0, "dp": 0.0, "u": "camerupt-4", "kart": true}, {"n": "Camerupt [Reverse Holo] #4", "p": 7.41, "p2": 149.95, "p3": 74.0, "d": -1.33, "dp": -15.2, "u": "camerupt-reverse-holo-4", "kart": true}, {"n": "Delcatty #5", "p": 20.0, "p2": 1009.81, "p3": 123.82, "d": -0.03, "dp": -0.1, "u": "delcatty-5", "kart": true}, {"n": "Delcatty [Reverse Holo] #5", "p": 16.48, "p2": 172.15, "p3": 58.85, "d": 2.27, "dp": 16.0, "u": "delcatty-reverse-holo-5", "kart": true}, {"n": "Dustox #6", "p": 14.86, "p2": 499.99, "p3": 79.36, "d": 0.0, "dp": 0.0, "u": "dustox-6", "kart": true}, {"n": "Dustox [Reverse Holo] #6", "p": 10.25, "p2": 328.36, "p3": 36.81, "d": 0.0, "dp": 0.0, "u": "dustox-reverse-holo-6", "kart": true}, {"n": "Gardevoir #7", "p": 11.89, "p2": null, "p3": null, "d": -0.83, "dp": -6.5, "u": "gardevoir-7", "kart": true}, {"n": "Gardevoir [Holo] #7", "p": 43.68, "p2": 5917.0, "p3": 268.48, "d": 5.68, "dp": 14.9, "u": "gardevoir-holo-7", "kart": true}, {"n": "Gardevoir [Kevin Nguyen] #7", "p": null, "p2": null, "p3": null, "d": 0.0, "dp": 0.0, "u": "gardevoir-kevin-nguyen-7", "kart": true}, {"n": "Gardevoir [Reverse Holo] #7", "p": 39.57, "p2": 1251.84, "p3": 81.89, "d": 0.36, "dp": 0.9, "u": "gardevoir-reverse-holo-7", "kart": true}, {"n": "Hariyama #8", "p": 8.63, "p2": 981.43, "p3": 46.54, "d": 0.0, "dp": 0.0, "u": "hariyama-8", "kart": true}, {"n": "Hariyama [Reverse Holo] #8", "p": 6.39, "p2": 61.0, "p3": 37.21, "d": 0.0, "dp": 0.0, "u": "hariyama-reverse-holo-8", "kart": true}, {"n": "Manectric #9", "p": 15.11, "p2": 366.23, "p3": 65.72, "d": 1.71, "dp": 12.8, "u": "manectric-9", "kart": true}, {"n": "Manectric [Reverse Holo] #9", "p": 8.91, "p2": 299.99, "p3": 48.0, "d": 0.43, "dp": 5.1, "u": "manectric-reverse-holo-9", "kart": true}, {"n": "Mightyena #10", "p": 17.08, "p2": 667.52, "p3": 53.02, "d": -0.76, "dp": -4.3, "u": "mightyena-10", "kart": true}, {"n": "Mightyena [Reverse Holo] #10", "p": 9.25, "p2": 103.5, "p3": 54.12, "d": 0.13, "dp": 1.4, "u": "mightyena-reverse-holo-10", "kart": true}, {"n": "Sceptile #11", "p": 49.74, "p2": 5100.0, "p3": 351.28, "d": -5.26, "dp": -9.6, "u": "sceptile-11", "kart": true}, {"n": "Sceptile [Reverse Holo] #11", "p": 31.75, "p2": 321.01, "p3": 151.31, "d": 0.0, "dp": 0.0, "u": "sceptile-reverse-holo-11", "kart": true}, {"n": "Slaking #12", "p": 10.92, "p2": 830.0, "p3": 84.46, "d": -0.65, "dp": -5.6, "u": "slaking-12", "kart": true}, {"n": "Slaking [Reverse Holo] #12", "p": 12.49, "p2": 152.47, "p3": 70.9, "d": 0.25, "dp": 2.0, "u": "slaking-reverse-holo-12", "kart": true}, {"n": "Swampert #13", "p": 28.51, "p2": 4013.65, "p3": 292.08, "d": 0.49, "dp": 1.7, "u": "swampert-13", "kart": true}, {"n": "Swampert [Reverse Holo] #13", "p": 32.5, "p2": 362.42, "p3": 107.86, "d": -0.74, "dp": -2.2, "u": "swampert-reverse-holo-13", "kart": true}, {"n": "Wailord #14", "p": 15.1, "p2": 494.24, "p3": 104.21, "d": -0.53, "dp": -3.4, "u": "wailord-14", "kart": true}, {"n": "Wailord [Reverse Holo] #14", "p": 17.23, "p2": 562.95, "p3": 56.02, "d": 0.0, "dp": 0.0, "u": "wailord-reverse-holo-14", "kart": true}, {"n": "Blaziken #15", "p": 3.51, "p2": 105.21, "p3": 33.0, "d": 0.51, "dp": 17.0, "u": "blaziken-15", "kart": true}, {"n": "Blaziken [Reverse Holo] #15", "p": 22.81, "p2": 420.0, "p3": 119.19, "d": -2.18, "dp": -8.7, "u": "blaziken-reverse-holo-15", "kart": true}, {"n": "Breloom #16", "p": 2.13, "p2": 51.39, "p3": 28.0, "d": -0.01, "dp": -0.5, "u": "breloom-16", "kart": true}, {"n": "Breloom [Reverse Holo] #16", "p": 11.5, "p2": 129.94, "p3": 40.0, "d": 1.51, "dp": 15.1, "u": "breloom-reverse-holo-16", "kart": true}, {"n": "Donphan #17", "p": 2.0, "p2": 56.77, "p3": 19.88, "d": 0.0, "dp": 0.0, "u": "donphan-17", "kart": true}, {"n": "Donphan [Reverse Holo] #17", "p": 8.93, "p2": 400.0, "p3": 40.0, "d": 2.09, "dp": 30.6, "u": "donphan-reverse-holo-17", "kart": true}, {"n": "Nosepass #18", "p": 1.72, "p2": 120.0, "p3": 23.6, "d": 0.18, "dp": 11.7, "u": "nosepass-18", "kart": true}, {"n": "Nosepass [Reverse Holo] #18", "p": 6.62, "p2": 115.03, "p3": 16.74, "d": -1.88, "dp": -22.1, "u": "nosepass-reverse-holo-18", "kart": true}, {"n": "Pelipper #19", "p": 1.74, "p2": 88.22, "p3": 42.5, "d": 0.06, "dp": 3.6, "u": "pelipper-19", "kart": true}, {"n": "Pelipper [Reverse Holo] #19", "p": 6.21, "p2": 89.98, "p3": 46.97, "d": 0.21, "dp": 3.5, "u": "pelipper-reverse-holo-19", "kart": true}, {"n": "Sceptile #20", "p": 7.83, "p2": 61.0, "p3": 39.97, "d": 0.3, "dp": 4.0, "u": "sceptile-20", "kart": true}, {"n": "Sceptile [Reverse Holo] #20", "p": 23.64, "p2": 185.79, "p3": 100.0, "d": 2.43, "dp": 11.5, "u": "sceptile-reverse-holo-20", "kart": true}, {"n": "Seaking #21", "p": 1.51, "p2": 53.0, "p3": 44.0, "d": 0.03, "dp": 2.0, "u": "seaking-21", "kart": true}, {"n": "Seaking [Reverse Holo] #21", "p": 9.75, "p2": 143.69, "p3": 65.99, "d": 0.75, "dp": 8.3, "u": "seaking-reverse-holo-21", "kart": true}, {"n": "Sharpedo #22", "p": 3.0, "p2": 165.53, "p3": 42.4, "d": -0.14, "dp": -4.5, "u": "sharpedo-22", "kart": true}, {"n": "Sharpedo [Reverse Holo] #22", "p": 9.78, "p2": 98.7, "p3": 57.5, "d": -2.08, "dp": -17.5, "u": "sharpedo-reverse-holo-22", "kart": true}, {"n": "Swampert #23", "p": 4.2, "p2": 77.54, "p3": 64.99, "d": 0.19, "dp": 4.7, "u": "swampert-23", "kart": true}, {"n": "Swampert [Reverse Holo] #23", "p": 20.6, "p2": 249.78, "p3": 132.09, "d": -1.39, "dp": -6.3, "u": "swampert-reverse-holo-23", "kart": true}, {"n": "Weezing #24", "p": 2.32, "p2": 63.0, "p3": 52.84, "d": 0.0, "dp": 0.0, "u": "weezing-24", "kart": true}, {"n": "Weezing [Reverse Holo] #24", "p": 10.0, "p2": 466.25, "p3": 34.74, "d": 1.29, "dp": 14.8, "u": "weezing-reverse-holo-24", "kart": true}, {"n": "Aron #25", "p": 2.78, "p2": 56.41, "p3": 22.0, "d": 0.14, "dp": 5.3, "u": "aron-25", "kart": true}, {"n": "Aron [Reverse Holo] #25", "p": 7.5, "p2": 252.56, "p3": 76.0, "d": 0.76, "dp": 11.3, "u": "aron-reverse-holo-25", "kart": true}, {"n": "Cascoon #26", "p": 2.66, "p2": 35.0, "p3": 15.0, "d": 0.17, "dp": 6.8, "u": "cascoon-26", "kart": true}, {"n": "Cascoon [Reverse Holo] #26", "p": 7.86, "p2": 279.26, "p3": 24.99, "d": 0.52, "dp": 7.1, "u": "cascoon-reverse-holo-26", "kart": true}, {"n": "Combusken #27", "p": 1.6, "p2": 299.99, "p3": 24.21, "d": 0.0, "dp": 0.0, "u": "combusken-27", "kart": true}, {"n": "Combusken [Reverse Holo] #27", "p": 13.99, "p2": 374.97, "p3": 47.75, "d": -0.68, "dp": -4.6, "u": "combusken-reverse-holo-27", "kart": true}, {"n": "Combusken #28", "p": 3.0, "p2": 69.43, "p3": 43.0, "d": 0.0, "dp": 0.0, "u": "combusken-28", "kart": true}, {"n": "Combusken [Reverse Holo] #28", "p": 13.49, "p2": 165.01, "p3": 46.53, "d": -0.02, "dp": -0.1, "u": "combusken-reverse-holo-28", "kart": true}, {"n": "Delcatty #29", "p": 1.74, "p2": 163.31, "p3": 37.25, "d": -0.13, "dp": -7.0, "u": "delcatty-29", "kart": true}, {"n": "Delcatty [Reverse Holo] #29", "p": 7.49, "p2": 199.74, "p3": 74.25, "d": -0.06, "dp": -0.8, "u": "delcatty-reverse-holo-29", "kart": true}, {"n": "Electrike #30", "p": 1.77, "p2": 91.59, "p3": 18.3, "d": 0.0, "dp": 0.0, "u": "electrike-30", "kart": true}, {"n": "Electrike [Reverse Holo] #30", "p": 9.25, "p2": 111.62, "p3": 36.0, "d": 1.09, "dp": 13.4, "u": "electrike-reverse-holo-30", "kart": true}, {"n": "Grovyle #31", "p": 2.12, "p2": 109.27, "p3": 36.89, "d": 0.07, "dp": 3.4, "u": "grovyle-31", "kart": true}, {"n": "Grovyle [Reverse Holo] #31", "p": 14.51, "p2": 160.1, "p3": 78.4, "d": 1.49, "dp": 11.4, "u": "grovyle-reverse-holo-31", "kart": true}, {"n": "Grovyle #32", "p": 3.68, "p2": 64.59, "p3": 36.0, "d": 0.22, "dp": 6.4, "u": "grovyle-32", "kart": true}, {"n": "Grovyle [Reverse Holo] #32", "p": 16.0, "p2": 250.0, "p3": 58.0, "d": 3.07, "dp": 23.7, "u": "grovyle-reverse-holo-32", "kart": true}, {"n": "Hariyama #33", "p": 1.36, "p2": 55.0, "p3": 46.0, "d": 0.51, "dp": 60.0, "u": "hariyama-33", "kart": true}, {"n": "Hariyama [Reverse Holo] #33", "p": 5.0, "p2": 79.9, "p3": 28.85, "d": 0.0, "dp": 0.0, "u": "hariyama-reverse-holo-33", "kart": true}, {"n": "Kirlia #34", "p": 2.4, "p2": 52.79, "p3": 31.95, "d": 0.12, "dp": 5.3, "u": "kirlia-34", "kart": true}, {"n": "Kirlia [Reverse Holo] #34", "p": 14.69, "p2": 435.0, "p3": 112.77, "d": -0.19, "dp": -1.3, "u": "kirlia-reverse-holo-34", "kart": true}, {"n": "Kirlia #35", "p": 2.59, "p2": 255.0, "p3": 30.0, "d": -0.16, "dp": -5.8, "u": "kirlia-35", "kart": true}, {"n": "Kirlia [Reverse Holo] #35", "p": 11.69, "p2": 1154.58, "p3": 85.0, "d": 1.19, "dp": 11.3, "u": "kirlia-reverse-holo-35", "kart": true}, {"n": "Lairon #36", "p": 2.03, "p2": 49.89, "p3": 33.0, "d": 0.04, "dp": 2.0, "u": "lairon-36", "kart": true}, {"n": "Lairon [Reverse Holo] #36", "p": 8.77, "p2": 107.0, "p3": 43.0, "d": 1.07, "dp": 13.9, "u": "lairon-reverse-holo-36", "kart": true}, {"n": "Lairon #37", "p": 2.08, "p2": 60.0, "p3": 30.18, "d": 0.03, "dp": 1.5, "u": "lairon-37", "kart": true}, {"n": "Lairon [Reverse Holo] #37", "p": 5.99, "p2": 89.94, "p3": 54.82, "d": 0.0, "dp": 0.0, "u": "lairon-reverse-holo-37", "kart": true}, {"n": "Linoone #38", "p": 2.0, "p2": 23.0, "p3": 19.38, "d": 0.0, "dp": 0.0, "u": "linoone-38", "kart": true}, {"n": "Linoone [Reverse Holo] #38", "p": 8.6, "p2": 191.99, "p3": 43.89, "d": 0.6, "dp": 7.5, "u": "linoone-reverse-holo-38", "kart": true}, {"n": "Manectric #39", "p": 1.76, "p2": 42.0, "p3": 34.99, "d": -0.02, "dp": -1.1, "u": "manectric-39", "kart": true}, {"n": "Manectric [Reverse Holo] #39", "p": 7.27, "p2": 310.0, "p3": 41.0, "d": 0.0, "dp": 0.0, "u": "manectric-reverse-holo-39", "kart": true}, {"n": "Marshtomp #40", "p": 1.99, "p2": 77.49, "p3": 19.99, "d": 0.0, "dp": 0.0, "u": "marshtomp-40", "kart": true}, {"n": "Marshtomp [Reverse Holo] #40", "p": 22.77, "p2": 603.17, "p3": 51.0, "d": 4.37, "dp": 23.8, "u": "marshtomp-reverse-holo-40", "kart": true}, {"n": "Marshtomp #41", "p": 3.91, "p2": 49.5, "p3": 39.99, "d": 0.04, "dp": 1.0, "u": "marshtomp-41", "kart": true}, {"n": "Marshtomp [Reverse Holo] #41", "p": 16.98, "p2": 200.96, "p3": 68.0, "d": -0.54, "dp": -3.1, "u": "marshtomp-reverse-holo-41", "kart": true}, {"n": "Mightyena #42", "p": 2.1, "p2": 100.0, "p3": 20.28, "d": -0.09, "dp": -4.1, "u": "mightyena-42", "kart": true}, {"n": "Mightyena [Reverse Holo] #42", "p": 8.0, "p2": 126.23, "p3": 57.4, "d": -1.62, "dp": -16.8, "u": "mightyena-reverse-holo-42", "kart": true}, {"n": "Silcoon #43", "p": 1.97, "p2": 61.6, "p3": 10.77, "d": -0.02, "dp": -1.0, "u": "silcoon-43", "kart": true}, {"n": "Silcoon [Reverse Holo] #43", "p": 9.99, "p2": 129.99, "p3": 57.48, "d": 0.0, "dp": 0.0, "u": "silcoon-reverse-holo-43", "kart": true}, {"n": "Skitty #44", "p": 8.41, "p2": 108.54, "p3": 24.99, "d": 0.56, "dp": 7.1, "u": "skitty-44", "kart": true}, {"n": "Skitty [Reverse Holo] #44", "p": 10.0, "p2": 72.5, "p3": 58.56, "d": 0.24, "dp": 2.5, "u": "skitty-reverse-holo-44", "kart": true}, {"n": "Slakoth #45", "p": 2.89, "p2": 165.95, "p3": 59.99, "d": -0.04, "dp": -1.4, "u": "slakoth-45", "kart": true}, {"n": "Slakoth [Reverse Holo] #45", "p": 6.73, "p2": 80.33, "p3": 69.03, "d": 1.7, "dp": 33.8, "u": "slakoth-reverse-holo-45", "kart": true}, {"n": "Swellow #46", "p": 1.29, "p2": 90.0, "p3": 74.59, "d": -0.15, "dp": -10.4, "u": "swellow-46", "kart": true}, {"n": "Swellow [Reverse Holo] #46", "p": 7.94, "p2": 149.99, "p3": 28.58, "d": 0.0, "dp": 0.0, "u": "swellow-reverse-holo-46", "kart": true}, {"n": "Vigoroth #47", "p": 1.44, "p2": 41.0, "p3": 33.74, "d": -0.09, "dp": -5.9, "u": "vigoroth-47", "kart": true}, {"n": "Vigoroth [Reverse Holo] #47", "p": 7.59, "p2": 89.87, "p3": 24.99, "d": 1.6, "dp": 26.7, "u": "vigoroth-reverse-holo-47", "kart": true}, {"n": "Wailmer #48", "p": 1.78, "p2": 69.99, "p3": 20.02, "d": -0.06, "dp": -3.3, "u": "wailmer-48", "kart": true}, {"n": "Wailmer [Reverse Holo] #48", "p": 15.25, "p2": 180.78, "p3": 30.0, "d": 0.17, "dp": 1.1, "u": "wailmer-reverse-holo-48", "kart": true}, {"n": "Aron #49", "p": 1.04, "p2": 69.99, "p3": 8.89, "d": -0.16, "dp": -13.3, "u": "aron-49", "kart": true}, {"n": "Aron [Reverse Holo] #49", "p": 8.0, "p2": 109.95, "p3": 34.0, "d": 0.0, "dp": 0.0, "u": "aron-reverse-holo-49", "kart": true}, {"n": "Aron #50", "p": 1.21, "p2": 69.99, "p3": 16.75, "d": -0.04, "dp": -3.2, "u": "aron-50", "kart": true}, {"n": "Aron [Reverse Holo] #50", "p": 9.39, "p2": 124.38, "p3": 76.0, "d": -0.04, "dp": -0.4, "u": "aron-reverse-holo-50", "kart": true}, {"n": "Carvanha #51", "p": 0.99, "p2": 69.99, "p3": 11.11, "d": 0.0, "dp": 0.0, "u": "carvanha-51", "kart": true}, {"n": "Carvanha [Reverse Holo] #51", "p": 8.36, "p2": 163.95, "p3": 35.89, "d": 0.42, "dp": 5.3, "u": "carvanha-reverse-holo-51", "kart": true}, {"n": "Electrike #52", "p": 1.36, "p2": 54.0, "p3": 22.73, "d": 0.06, "dp": 4.6, "u": "electrike-52", "kart": true}, {"n": "Electrike [Reverse Holo] #52", "p": 6.78, "p2": 261.0, "p3": 44.0, "d": 1.27, "dp": 23.0, "u": "electrike-reverse-holo-52", "kart": true}, {"n": "Electrike #53", "p": 1.44, "p2": 69.99, "p3": 14.98, "d": 0.45, "dp": 45.5, "u": "electrike-53", "kart": true}, {"n": "Electrike [Reverse Holo] #53", "p": 9.0, "p2": 96.0, "p3": 27.5, "d": 0.0, "dp": 0.0, "u": "electrike-reverse-holo-53", "kart": true}, {"n": "Koffing #54", "p": 1.38, "p2": 62.68, "p3": 21.19, "d": 0.28, "dp": 25.5, "u": "koffing-54", "kart": true}, {"n": "Koffing [Reverse Holo] #54", "p": 14.18, "p2": 166.5, "p3": 65.0, "d": 0.52, "dp": 3.8, "u": "koffing-reverse-holo-54", "kart": true}, {"n": "Goldeen #55", "p": 0.91, "p2": 41.79, "p3": 9.51, "d": -0.25, "dp": -21.6, "u": "goldeen-55", "kart": true}, {"n": "Goldeen [Reverse Holo] #55", "p": 6.45, "p2": 410.83, "p3": 61.0, "d": 0.45, "dp": 7.5, "u": "goldeen-reverse-holo-55", "kart": true}, {"n": "Makuhita #56", "p": 0.87, "p2": 53.0, "p3": 44.0, "d": 0.5, "dp": 135.1, "u": "makuhita-56", "kart": true}, {"n": "Makuhita [Reverse Holo] #56", "p": 4.99, "p2": 95.36, "p3": 52.97, "d": 0.66, "dp": 15.2, "u": "makuhita-reverse-holo-56", "kart": true}, {"n": "Makuhita #57", "p": 1.0, "p2": 65.0, "p3": 53.0, "d": -0.04, "dp": -3.8, "u": "makuhita-57", "kart": true}, {"n": "Makuhita [Reverse Holo] #57", "p": 4.92, "p2": 83.2, "p3": 50.34, "d": -0.4, "dp": -7.5, "u": "makuhita-reverse-holo-57", "kart": true}, {"n": "Makuhita #58", "p": 1.28, "p2": 59.99, "p3": 7.69, "d": -0.17, "dp": -11.7, "u": "makuhita-58", "kart": true}, {"n": "Makuhita [Reverse Holo] #58", "p": 3.66, "p2": 60.0, "p3": 52.0, "d": 0.18, "dp": 5.2, "u": "makuhita-reverse-holo-58", "kart": true}, {"n": "Mudkip #59", "p": 4.39, "p2": 84.17, "p3": 25.33, "d": 0.0, "dp": 0.0, "u": "mudkip-59", "kart": true}, {"n": "Mudkip [Jumbo] #59", "p": 0.99, "p2": null, "p3": null, "d": 0.0, "dp": 0.0, "u": "mudkip-jumbo-59", "kart": true}, {"n": "Mudkip [Reverse Holo] #59", "p": 19.49, "p2": 3285.45, "p3": 144.18, "d": -1.24, "dp": -6.0, "u": "mudkip-reverse-holo-59", "kart": true}, {"n": "Mudkip #60", "p": 2.74, "p2": 350.19, "p3": 30.0, "d": 0.24, "dp": 9.6, "u": "mudkip-60", "kart": true}, {"n": "Mudkip [Reverse Holo] #60", "p": 32.49, "p2": 308.8, "p3": 138.33, "d": 4.62, "dp": 16.6, "u": "mudkip-reverse-holo-60", "kart": true}, {"n": "Numel #61", "p": 1.39, "p2": 75.0, "p3": 31.0, "d": -0.08, "dp": -5.4, "u": "numel-61", "kart": true}, {"n": "Numel [Reverse Holo] #61", "p": 7.99, "p2": 106.14, "p3": 75.47, "d": 0.37, "dp": 4.9, "u": "numel-reverse-holo-61", "kart": true}, {"n": "Phanpy #62", "p": 2.46, "p2": 95.8, "p3": 15.0, "d": -0.08, "dp": -3.1, "u": "phanpy-62", "kart": true}, {"n": "Phanpy [Reverse Holo] #62", "p": 15.6, "p2": 449.95, "p3": 54.18, "d": 0.38, "dp": 2.5, "u": "phanpy-reverse-holo-62", "kart": true}, {"n": "Poochyena #63", "p": 1.14, "p2": 55.0, "p3": 19.0, "d": 0.14, "dp": 14.0, "u": "poochyena-63", "kart": true}, {"n": "Poochyena [Reverse Holo] #63", "p": 8.78, "p2": 205.82, "p3": 36.99, "d": 1.53, "dp": 21.1, "u": "poochyena-reverse-holo-63", "kart": true}, {"n": "Poochyena #64", "p": 1.43, "p2": 53.0, "p3": 44.0, "d": 0.04, "dp": 2.9, "u": "poochyena-64", "kart": true}, {"n": "Poochyena [Reverse Holo] #64", "p": 10.76, "p2": 114.99, "p3": 27.5, "d": 1.18, "dp": 12.3, "u": "poochyena-reverse-holo-64", "kart": true}, {"n": "Poochyena #65", "p": 1.49, "p2": 70.82, "p3": 14.98, "d": -0.11, "dp": -6.9, "u": "poochyena-65", "kart": true}, {"n": "Poochyena [Reverse Holo] #65", "p": 6.84, "p2": 81.91, "p3": 66.26, "d": 1.65, "dp": 31.8, "u": "poochyena-reverse-holo-65", "kart": true}, {"n": "Ralts #66", "p": 1.75, "p2": 167.5, "p3": 11.0, "d": 0.14, "dp": 8.7, "u": "ralts-66", "kart": true}, {"n": "Ralts [Reverse Holo] #66", "p": 12.97, "p2": 159.81, "p3": 47.5, "d": 0.0, "dp": 0.0, "u": "ralts-reverse-holo-66", "kart": true}, {"n": "Ralts #67", "p": 2.5, "p2": 200.0, "p3": 8.07, "d": 0.0, "dp": 0.0, "u": "ralts-67", "kart": true}, {"n": "Ralts [Reverse Holo] #67", "p": 15.85, "p2": 177.0, "p3": 51.53, "d": 1.13, "dp": 7.7, "u": "ralts-reverse-holo-67", "kart": true}, {"n": "Ralts #68", "p": 2.55, "p2": 67.75, "p3": 42.69, "d": 0.34, "dp": 15.4, "u": "ralts-68", "kart": true}, {"n": "Ralts [Reverse Holo] #68", "p": 11.1, "p2": 129.93, "p3": 67.81, "d": 1.09, "dp": 10.9, "u": "ralts-reverse-holo-68", "kart": true}, {"n": "Shroomish #69", "p": 1.14, "p2": 54.5, "p3": 27.49, "d": 0.0, "dp": 0.0, "u": "shroomish-69", "kart": true}, {"n": "Shroomish [Reverse Holo] #69", "p": 6.26, "p2": 227.58, "p3": 66.0, "d": 0.0, "dp": 0.0, "u": "shroomish-reverse-holo-69", "kart": true}, {"n": "Skitty #70", "p": 1.0, "p2": 177.12, "p3": 10.0, "d": -0.25, "dp": -20.0, "u": "skitty-70", "kart": true}, {"n": "Skitty [Reverse Holo] #70", "p": 6.99, "p2": 419.99, "p3": 77.49, "d": 0.39, "dp": 5.9, "u": "skitty-reverse-holo-70", "kart": true}, {"n": "Skitty #71", "p": 2.12, "p2": 61.59, "p3": 20.1, "d": 0.0, "dp": 0.0, "u": "skitty-71", "kart": true}, {"n": "Skitty [Reverse Holo] #71", "p": 13.06, "p2": 432.36, "p3": 30.0, "d": 2.06, "dp": 18.7, "u": "skitty-reverse-holo-71", "kart": true}, {"n": "Taillow #72", "p": 1.01, "p2": 36.99, "p3": 5.4, "d": 0.14, "dp": 16.1, "u": "taillow-72", "kart": true}, {"n": "Taillow [Reverse Holo] #72", "p": 6.5, "p2": 89.9, "p3": 39.61, "d": 0.51, "dp": 8.5, "u": "taillow-reverse-holo-72", "kart": true}, {"n": "Torchic #73", "p": 1.41, "p2": 100.0, "p3": 29.99, "d": -0.09, "dp": -6.0, "u": "torchic-73", "kart": true}, {"n": "Torchic [Reverse Holo] #73", "p": 16.21, "p2": 214.28, "p3": 142.5, "d": -2.24, "dp": -12.1, "u": "torchic-reverse-holo-73", "kart": true}, {"n": "Torchic #74", "p": 2.05, "p2": 60.0, "p3": 27.0, "d": -0.41, "dp": -16.7, "u": "torchic-74", "kart": true}, {"n": "Torchic [Jumbo] #74", "p": 0.99, "p2": null, "p3": null, "d": 0.0, "dp": 0.0, "u": "torchic-jumbo-74", "kart": true}, {"n": "Torchic [Reverse Holo] #74", "p": 12.56, "p2": 2050.65, "p3": 122.5, "d": -0.96, "dp": -7.1, "u": "torchic-reverse-holo-74", "kart": true}, {"n": "Treecko #75", "p": 1.42, "p2": 83.32, "p3": 26.0, "d": -0.28, "dp": -16.5, "u": "treecko-75", "kart": true}, {"n": "Treecko [Reverse Holo] #75", "p": 12.5, "p2": 149.97, "p3": 74.99, "d": 0.75, "dp": 6.4, "u": "treecko-reverse-holo-75", "kart": true}, {"n": "Treecko #76", "p": 2.49, "p2": 196.35, "p3": 66.0, "d": 0.13, "dp": 5.5, "u": "treecko-76", "kart": true}, {"n": "Treecko [Reverse Holo] #76", "p": 13.84, "p2": 8500.0, "p3": 86.25, "d": 2.85, "dp": 25.9, "u": "treecko-reverse-holo-76", "kart": true}, {"n": "Wingull #77", "p": 0.99, "p2": 59.97, "p3": 11.0, "d": -0.39, "dp": -28.3, "u": "wingull-77", "kart": true}, {"n": "Wingull [Reverse Holo] #77", "p": 10.0, "p2": 56.0, "p3": 55.0, "d": 3.27, "dp": 48.6, "u": "wingull-reverse-holo-77", "kart": true}, {"n": "Wurmple #78", "p": 1.77, "p2": 45.51, "p3": 11.99, "d": 0.22, "dp": 14.2, "u": "wurmple-78", "kart": true}, {"n": "Wurmple [Reverse Holo] #78", "p": 8.45, "p2": 248.11, "p3": 54.0, "d": 1.45, "dp": 20.7, "u": "wurmple-reverse-holo-78", "kart": true}, {"n": "Zigzagoon #79", "p": 1.44, "p2": 44.59, "p3": 35.24, "d": -0.02, "dp": -1.4, "u": "zigzagoon-79", "kart": true}, {"n": "Zigzagoon [Reverse Holo] #79", "p": 9.8, "p2": 129.85, "p3": 78.86, "d": -0.19, "dp": -1.9, "u": "zigzagoon-reverse-holo-79", "kart": true}, {"n": "Energy Removal 2 #80", "p": 1.36, "p2": 45.48, "p3": 5.99, "d": -0.19, "dp": -12.3, "u": "energy-removal-2-80", "kart": true}, {"n": "Energy Removal 2 [Reverse Holo] #80", "p": 3.82, "p2": 34.0, "p3": 11.06, "d": 0.74, "dp": 24.0, "u": "energy-removal-2-reverse-holo-80", "kart": true}, {"n": "Energy Restore #81", "p": 0.52, "p2": 49.99, "p3": 19.99, "d": -0.15, "dp": -22.4, "u": "energy-restore-81", "kart": true}, {"n": "Energy Restore [Reverse Holo] #81", "p": 3.52, "p2": 61.61, "p3": 19.96, "d": 0.36, "dp": 11.4, "u": "energy-restore-reverse-holo-81", "kart": true}, {"n": "Energy Switch #82", "p": 3.15, "p2": 69.99, "p3": 16.74, "d": 0.37, "dp": 13.3, "u": "energy-switch-82", "kart": true}, {"n": "Energy Switch [Reverse Holo] #82", "p": 9.69, "p2": 126.89, "p3": 13.3, "d": 0.0, "dp": 0.0, "u": "energy-switch-reverse-holo-82", "kart": true}, {"n": "Lady Outing #83", "p": 1.09, "p2": 70.0, "p3": 9.0, "d": 0.24, "dp": 28.2, "u": "lady-outing-83", "kart": true}, {"n": "Lady Outing [Reverse Holo] #83", "p": 4.16, "p2": 300.0, "p3": 29.99, "d": -0.06, "dp": -1.4, "u": "lady-outing-reverse-holo-83", "kart": true}, {"n": "Lum Berry #84", "p": 1.12, "p2": 40.1, "p3": 14.0, "d": 0.11, "dp": 10.9, "u": "lum-berry-84", "kart": true}, {"n": "Lum Berry [Reverse Holo] #84", "p": 3.1, "p2": 59.93, "p3": 24.06, "d": 0.1, "dp": 3.3, "u": "lum-berry-reverse-holo-84", "kart": true}, {"n": "Oran Berry #85", "p": 1.05, "p2": 42.83, "p3": 8.5, "d": -0.13, "dp": -11.0, "u": "oran-berry-85", "kart": true}, {"n": "Oran Berry [Jumbo] #85", "p": null, "p2": null, "p3": null, "d": 0.0, "dp": 0.0, "u": "oran-berry-jumbo-85", "kart": true}, {"n": "Oran Berry [Reverse Holo] #85", "p": 5.49, "p2": 80.0, "p3": 57.76, "d": 0.98, "dp": 21.7, "u": "oran-berry-reverse-holo-85", "kart": true}, {"n": "Oran Berry [Winner] #85", "p": 22.38, "p2": 69.0, "p3": 33.0, "d": 0.0, "dp": 0.0, "u": "oran-berry-winner-85", "kart": true}, {"n": "Poke Ball #86", "p": 1.22, "p2": 150.0, "p3": 13.0, "d": 0.41, "dp": 50.6, "u": "poke-ball-86", "kart": true}, {"n": "Poke Ball [Reverse Holo] #86", "p": 6.99, "p2": 99.73, "p3": 65.0, "d": 0.0, "dp": 0.0, "u": "poke-ball-reverse-holo-86", "kart": true}, {"n": "Pokemon Reversal #87", "p": 3.03, "p2": 60.64, "p3": 12.52, "d": 0.53, "dp": 21.2, "u": "pokemon-reversal-87", "kart": true}, {"n": "Pokemon Reversal [Reverse Holo] #87", "p": 9.0, "p2": 89.82, "p3": 40.85, "d": 3.01, "dp": 50.3, "u": "pokemon-reversal-reverse-holo-87", "kart": true}, {"n": "Pokenav #88", "p": 0.5, "p2": 36.8, "p3": 15.07, "d": -0.18, "dp": -26.5, "u": "pokenav-88", "kart": true}, {"n": "Pokenav [Reverse Holo] #88", "p": 3.89, "p2": 68.81, "p3": 18.74, "d": 0.0, "dp": 0.0, "u": "pokenav-reverse-holo-88", "kart": true}, {"n": "Professor Birch #89", "p": 0.49, "p2": 40.49, "p3": 8.65, "d": -0.56, "dp": -53.3, "u": "professor-birch-89", "kart": true}, {"n": "Professor Birch [Reverse Holo] #89", "p": 3.77, "p2": 66.7, "p3": 15.5, "d": 0.1, "dp": 2.7, "u": "professor-birch-reverse-holo-89", "kart": true}, {"n": "Energy Search #90", "p": 0.33, "p2": 67.28, "p3": 9.26, "d": -0.43, "dp": -56.6, "u": "energy-search-90", "kart": true}, {"n": "Energy Search [Reverse Holo] #90", "p": 4.64, "p2": 140.0, "p3": 13.91, "d": 0.14, "dp": 3.1, "u": "energy-search-reverse-holo-90", "kart": true}, {"n": "Potion #91", "p": 0.25, "p2": 32.4, "p3": 9.99, "d": 0.01, "dp": 4.2, "u": "potion-91", "kart": true}, {"n": "Potion [Reverse Holo] #91", "p": 3.42, "p2": 217.83, "p3": 23.5, "d": 0.54, "dp": 18.8, "u": "potion-reverse-holo-91", "kart": true}, {"n": "Switch #92", "p": 0.87, "p2": 64.13, "p3": 14.0, "d": -0.23, "dp": -20.9, "u": "switch-92", "kart": true}, {"n": "Switch [Reverse Holo] #92", "p": 4.12, "p2": 72.05, "p3": 28.0, "d": -0.09, "dp": -2.1, "u": "switch-reverse-holo-92", "kart": true}, {"n": "Darkness Energy #93", "p": 1.83, "p2": 39.57, "p3": 7.8, "d": 0.14, "dp": 8.3, "u": "darkness-energy-93", "kart": true}, {"n": "Darkness Energy [Holo] #93", "p": 6.65, "p2": 236.92, "p3": 23.5, "d": 0.0, "dp": 0.0, "u": "darkness-energy-holo-93", "kart": true}, {"n": "Darkness Energy [Reverse Holo] #93", "p": 3.37, "p2": 59.9, "p3": 12.43, "d": 0.38, "dp": 12.7, "u": "darkness-energy-reverse-holo-93", "kart": true}, {"n": "Darkness Energy [Winner] #93", "p": 29.99, "p2": null, "p3": 99.99, "d": 0.04, "dp": 0.1, "u": "darkness-energy-winner-93", "kart": true}, {"n": "Metal Energy #94", "p": 1.2, "p2": 40.2, "p3": 26.0, "d": 0.18, "dp": 17.6, "u": "metal-energy-94", "kart": true}, {"n": "Metal Energy [Jumbo] #94", "p": null, "p2": null, "p3": null, "d": 0.0, "dp": 0.0, "u": "metal-energy-jumbo-94", "kart": true}, {"n": "Metal Energy [Reverse Holo] #94", "p": 4.72, "p2": 77.18, "p3": 18.0, "d": 0.0, "dp": 0.0, "u": "metal-energy-reverse-holo-94", "kart": true}, {"n": "Metal Energy [Winner] #94", "p": 36.61, "p2": null, "p3": 99.99, "d": 0.0, "dp": 0.0, "u": "metal-energy-winner-94", "kart": true}, {"n": "Rainbow Energy #95", "p": 1.51, "p2": 77.54, "p3": 9.5, "d": -0.02, "dp": -1.3, "u": "rainbow-energy-95", "kart": true}, {"n": "Rainbow Energy [Reverse Holo] #95", "p": 10.54, "p2": 135.25, "p3": 20.65, "d": 0.0, "dp": 0.0, "u": "rainbow-energy-reverse-holo-95", "kart": true}, {"n": "Chansey EX #96", "p": 51.69, "p2": 1069.42, "p3": 230.17, "d": 10.19, "dp": 24.6, "u": "chansey-ex-96", "kart": true}, {"n": "Electabuzz EX #97", "p": 37.73, "p2": 1750.0, "p3": 220.78, "d": -3.02, "dp": -7.4, "u": "electabuzz-ex-97", "kart": true}, {"n": "Hitmonchan EX #98", "p": 52.68, "p2": 916.0, "p3": 336.51, "d": 4.8, "dp": 10.0, "u": "hitmonchan-ex-98", "kart": true}, {"n": "Lapras EX #99", "p": 70.84, "p2": 938.25, "p3": 715.0, "d": 0.67, "dp": 1.0, "u": "lapras-ex-99", "kart": true}, {"n": "Magmar EX #100", "p": 37.25, "p2": 2579.61, "p3": 165.49, "d": 2.5, "dp": 7.2, "u": "magmar-ex-100", "kart": true}, {"n": "Mewtwo EX #101", "p": 198.31, "p2": 18274.75, "p3": 2017.1, "d": -1.69, "dp": -0.8, "u": "mewtwo-ex-101", "kart": true}, {"n": "Scyther EX #102", "p": 68.65, "p2": 1575.0, "p3": 352.85, "d": 12.88, "dp": 23.1, "u": "scyther-ex-102", "kart": true}, {"n": "Sneasel EX #103", "p": 48.0, "p2": 2681.2, "p3": 245.33, "d": 4.32, "dp": 9.9, "u": "sneasel-ex-103", "kart": true}, {"n": "Grass Energy #104", "p": 0.35, "p2": 41.21, "p3": 14.02, "d": -0.77, "dp": -68.8, "u": "grass-energy-104", "kart": true}, {"n": "Grass Energy [2005] #104", "p": 0.5, "p2": 109.0, "p3": null, "d": 0.0, "dp": 0.0, "u": "grass-energy-2005-104", "kart": true}, {"n": "Grass Energy [Professor Program 2004-2005] #104", "p": 90.0, "p2": null, "p3": null, "d": 0.0, "dp": 0.0, "u": "grass-energy-professor-program-2004-2005-104", "kart": true}, {"n": "Grass Energy [Reverse Holo] #104", "p": 7.19, "p2": 103.02, "p3": 13.26, "d": -0.11, "dp": -1.5, "u": "grass-energy-reverse-holo-104", "kart": true}, {"n": "Grass energy [2004] #104", "p": 0.5, "p2": null, "p3": 27.0, "d": 0.0, "dp": 0.0, "u": "grass-energy-2004-104", "kart": true}, {"n": "Fighting Energy #105", "p": 0.49, "p2": 34.0, "p3": 12.56, "d": 0.09, "dp": 22.5, "u": "fighting-energy-105", "kart": true}, {"n": "Fighting Energy [Reverse Holo] #105", "p": 8.99, "p2": 119.95, "p3": 7.5, "d": 0.0, "dp": 0.0, "u": "fighting-energy-reverse-holo-105", "kart": true}, {"n": "Water Energy #106", "p": 0.74, "p2": 39.09, "p3": 6.0, "d": -0.17, "dp": -18.7, "u": "water-energy-106", "kart": true}, {"n": "Water Energy [Professor Program 2004-2005] #106", "p": 22.01, "p2": null, "p3": null, "d": 0.0, "dp": 0.0, "u": "water-energy-professor-program-2004-2005-106", "kart": true}, {"n": "Water Energy [Reverse Holo] #106", "p": 11.6, "p2": 161.93, "p3": 23.0, "d": 3.4, "dp": 41.5, "u": "water-energy-reverse-holo-106", "kart": true}, {"n": "Psychic Energy #107", "p": 1.18, "p2": 59.5, "p3": 59.0, "d": -0.09, "dp": -7.1, "u": "psychic-energy-107", "kart": true}, {"n": "Psychic Energy [Reverse Holo] #107", "p": 9.11, "p2": 117.42, "p3": 32.59, "d": 0.35, "dp": 4.0, "u": "psychic-energy-reverse-holo-107", "kart": true}, {"n": "Fire Energy #108", "p": 0.33, "p2": 33.3, "p3": 11.25, "d": 0.0, "dp": 0.0, "u": "fire-energy-108", "kart": true}, {"n": "Fire Energy [Professor Program 2004-2005] #108", "p": 56.7, "p2": null, "p3": null, "d": 0.0, "dp": 0.0, "u": "fire-energy-professor-program-2004-2005-108", "kart": true}, {"n": "Fire Energy [Reverse Holo] #108", "p": 9.99, "p2": 118.01, "p3": 24.99, "d": 1.17, "dp": 13.3, "u": "fire-energy-reverse-holo-108", "kart": true}, {"n": "Lightning Energy #109", "p": 0.32, "p2": 33.8, "p3": 14.37, "d": -0.06, "dp": -15.8, "u": "lightning-energy-109", "kart": true}, {"n": "Lightning Energy [Professor Program] #109", "p": null, "p2": null, "p3": 54.99, "d": 0.0, "dp": 0.0, "u": "lightning-energy-professor-program-109", "kart": true}, {"n": "Lightning Energy [Reverse Holo] #109", "p": 6.2, "p2": 91.99, "p3": 11.32, "d": 0.0, "dp": 0.0, "u": "lightning-energy-reverse-holo-109", "kart": true}, {"n": "Booster Box", "p": 16245.7, "p2": null, "p3": null, "d": 0.0, "dp": 0.0, "u": "booster-box", "kart": true}, {"n": "Booster Pack", "p": 577.42, "p2": 340.0, "p3": 262.75, "d": -22.57, "dp": -3.8, "u": "booster-pack", "kart": true}, {"n": "Blister Pack", "p": 642.77, "p2": null, "p3": null, "d": 3.27, "dp": 0.5, "u": "blister-pack", "kart": true}]